dfdiff/__init__.py
dfdiff/dfdiff.py
dfdiff/py.typed
dfdiff-0.8.dist-info/METADATA
dfdiff-0.8.dist-info/WHEEL
dfdiff-0.8.dist-info/licenses/LICENSE
dfdiff-0.8.dist-info/RECORD
