Metadata-Version: 2.4
Name: dfdiff
Version: 0.8
Summary: Library that utilize the Python to quickly identify the differences between two DataFrame objects.
Project-URL: Homepage, https://github.com/andychien009/dfdiff
Project-URL: Issues, https://github.com/andychien009/dfdiff/issues
License-Expression: GPL-3.0
License-File: LICENSE
Requires-Python: >=3.12
Requires-Dist: numpy>=2.3.5
Requires-Dist: openpyxl>=3.1.5
Requires-Dist: pandas>=2.3.3
